graphite_opentsdb/app_settings.py
graphite_opentsdb/finder.py
graphite_opentsdb/autoconfig.py
graphite_opentsdb/models.py
graphite_opentsdb/version.py
graphite_opentsdb/tests.py
graphite_opentsdb/__init__.py
graphite_opentsdb-0.4.1.dist-info/WHEEL
graphite_opentsdb-0.4.1.dist-info/top_level.txt
graphite_opentsdb-0.4.1.dist-info/RECORD
graphite_opentsdb-0.4.1.dist-info/DESCRIPTION.rst
graphite_opentsdb-0.4.1.dist-info/metadata.json
graphite_opentsdb-0.4.1.dist-info/METADATA
