Metadata-Version: 2.0
Name: graphite-opentsdb
Version: 0.4.1
Summary: A graphite storage plugin for OpenTSDB.
Home-page: https://github.com/mikebryant/graphite-opentsdb-finder
Author: Mike Bryant
Author-email: mike@mikebryant.me.uk
License: UNKNOWN
Platform: UNKNOWN
Classifier: Development Status :: 3 - Alpha
Classifier: Environment :: Web Environment
Classifier: Framework :: Django
Classifier: Intended Audience :: Developers
Classifier: License :: OSI Approved :: GNU General Public License v3 or later (GPLv3+)
Classifier: Programming Language :: Python
Classifier: Programming Language :: Python :: 2
Classifier: Programming Language :: Python :: 2.6
Classifier: Programming Language :: Python :: 2.7
Classifier: Programming Language :: Python :: 3
Classifier: Programming Language :: Python :: 3.2
Classifier: Programming Language :: Python :: 3.3
Requires-Dist: django
Requires-Dist: django-cacheback
Requires-Dist: graphite-web
Requires-Dist: requests
